fuga/__init__.py
fuga/airflow.py
fuga/experiment.py
fuga/gcs.py
fuga/utils.py
fuga/cli/__init__.py
fuga/cli/environment.py
fuga/cli/experiment.py
fuga/cli/pod_operator.py
fuga/config/__init__.py
fuga/google/__init__.py
fuga/google/cloud/__init__.py
fuga/google/cloud/composer/__init__.py
fuga/google/cloud/composer/_http.py
fuga/google/cloud/composer/client.py
fuga/google/cloud/composer/environment.py
tests/__init__.py
tests/test_fuga.py
fuga-0.1.7.dist-info/LICENSE
fuga-0.1.7.dist-info/METADATA
fuga-0.1.7.dist-info/WHEEL
fuga-0.1.7.dist-info/entry_points.txt
fuga-0.1.7.dist-info/top_level.txt
fuga-0.1.7.dist-info/RECORD
