Metadata-Version: 2.1
Name: fuga
Version: 0.1.7
Summary: Fuga - Helper toolset for Google Cloud Cimposer
Home-page: https://github.com/ayemos/fuga
Author: Yuichiro Someya
Author-email: me@ayemos.me
License: MIT license
Keywords: fuga
Platform: UNKNOWN
Classifier: Development Status :: 4 - Beta
Classifier: Intended Audience :: Developers
Classifier: License :: OSI Approved :: MIT License
Classifier: Natural Language :: English
Classifier: Programming Language :: Python :: 3.6
Classifier: Programming Language :: Python :: 3.7
Requires-Dist: Click (>=6.0)
Requires-Dist: google-cloud-resource-manager (~=0.29.1)
Requires-Dist: google-cloud-storage (~=1.18.0)
Requires-Dist: cookiecutter (~=1.6.0)
Requires-Dist: GitPython (~=2.1.11)
Requires-Dist: pyyaml (~=4.2b1)
Requires-Dist: docker (~=4.0.2)
